keprep/__init__.py
keprep/cli.py
keprep/config.py
keprep/data/__init__.py
keprep/data/boilerplate.bib
keprep/data/keprep.json
keprep/data/quality_assurance/__init__.py
keprep/data/quality_assurance/reports.py
keprep/data/quality_assurance/templates/__init__.py
keprep/data/quality_assurance/templates/reports-spec.yml
keprep/interfaces/__init__.py
keprep/interfaces/bids/__init__.py
keprep/interfaces/bids/bids.py
keprep/interfaces/bids/utils.py
keprep/interfaces/mrtrix3.py
keprep/interfaces/reports/__init__.py
keprep/interfaces/reports/reports.py
keprep/keprep.py
keprep/workflows/base/__init__.py
keprep/workflows/base/messages.py
keprep/workflows/base/workflow.py
keprep/workflows/dwi/__init__.py
keprep/workflows/dwi/descriptions/base.py
keprep/workflows/dwi/descriptions/coregister.py
keprep/workflows/dwi/descriptions/eddy.py
keprep/workflows/dwi/descriptions/post_eddy.py
keprep/workflows/dwi/stages/__init__.py
keprep/workflows/dwi/stages/coregister.py
keprep/workflows/dwi/stages/derivatives.py
keprep/workflows/dwi/stages/eddy.py
keprep/workflows/dwi/stages/extract_b0.py
keprep/workflows/dwi/stages/post_eddy.py
keprep/workflows/dwi/utils.py
keprep/workflows/dwi/workflow.py
keprep-0.2.2.2.dist-info/AUTHORS.rst
keprep-0.2.2.2.dist-info/LICENSE
keprep-0.2.2.2.dist-info/METADATA
keprep-0.2.2.2.dist-info/WHEEL
keprep-0.2.2.2.dist-info/RECORD
