Metadata-Version: 2.3
Name: keprep
Version: 0.2.2.2
Summary: Minimally preprocessing TheBase dMRI data.
License: MIT
Keywords: neuroscience,MRI,data processing,automation,standardization
Author: Gal Kepler
Author-email: galkepler@gmail.com
Requires-Python: >=3.10,<4.0
Classifier: Development Status :: 3 - Alpha
Classifier: Intended Audience :: Science/Research
Classifier: License :: OSI Approved :: MIT License
Classifier: Programming Language :: Python :: 3
Classifier: Programming Language :: Python :: 3.10
Classifier: Programming Language :: Python :: 3.11
Classifier: Programming Language :: Python :: 3.12
Classifier: Programming Language :: Python :: 3.13
Classifier: Topic :: Scientific/Engineering :: Information Analysis
Requires-Dist: dipy (>=1.9.0,<2.0.0)
Requires-Dist: doc8 (>=1.1.1,<2.0.0)
Requires-Dist: flake8-pyproject (>=1.2.3,<2.0.0)
Requires-Dist: nipype (>=1.8.6,<2.0.0)
Requires-Dist: nireports (>=23.2.1,<24.0.0)
Requires-Dist: niworkflows (>=1.8.1,<2.0.0)
Requires-Dist: pre-commit (>=3.3.3,<4.0.0)
Requires-Dist: psutil (>=5.9.5,<6.0.0)
Requires-Dist: pytest (>=8.3.2,<9.0.0)
Requires-Dist: pyupgrade (>=3.9.0,<4.0.0)
Requires-Dist: sdcflows (>=2.5.1,<3.0.0)
Requires-Dist: setuptools (>=72.1.0,<73.0.0)
Requires-Dist: smriprep (>=0.12.1,<0.13.0)
Requires-Dist: templateflow (>=23.0.0,<24.0.0)
Requires-Dist: toml (>=0.10.2,<0.11.0)
Requires-Dist: tox (>=4.16.0,<5.0.0)
Project-URL: Documentation, https://KePrep.readthedocs.io
Project-URL: Homepage, https://pypi.org/project/KePrep
Project-URL: Repository, https://github.com/GalKepler/keprep
